tap_postgres/__init__.py
tap_postgres/db.py
tap_postgres/discovery_utils.py
tap_postgres/stream_utils.py
tap_postgres/sync_strategies/__init__.py
tap_postgres/sync_strategies/common.py
tap_postgres/sync_strategies/full_table.py
tap_postgres/sync_strategies/incremental.py
tap_postgres/sync_strategies/logical_replication.py
dp_pipelinewise_tap_postgres-1.8.14.dist-info/LICENSE
dp_pipelinewise_tap_postgres-1.8.14.dist-info/METADATA
dp_pipelinewise_tap_postgres-1.8.14.dist-info/WHEEL
dp_pipelinewise_tap_postgres-1.8.14.dist-info/entry_points.txt
dp_pipelinewise_tap_postgres-1.8.14.dist-info/top_level.txt
dp_pipelinewise_tap_postgres-1.8.14.dist-info/RECORD
