Metadata-Version: 2.1
Name: dp-pipelinewise-tap-postgres
Version: 1.8.14
Summary: Singer.io tap for extracting data from PostgresSQL - PipelineWise compatible
Home-page: https://github.com/ashalitkin/pipelinewise-tap-postgres
Author: TransferWise
License: UNKNOWN
Platform: UNKNOWN
Classifier: License :: OSI Approved :: GNU Affero General Public License v3
Classifier: Programming Language :: Python :: 3 :: Only
License-File: LICENSE
Requires-Dist: pipelinewise-singer-python (==1.*)
Requires-Dist: psycopg2-binary (==2.8.6)
Requires-Dist: strict-rfc3339 (==0.7)
Provides-Extra: test
Requires-Dist: pytest (==6.2.1) ; extra == 'test'
Requires-Dist: pylint (==2.6.0) ; extra == 'test'
Requires-Dist: pytest-cov (==2.10.1) ; extra == 'test'
